k3fmt/__init__.py
k3fmt/strutil.py
k3fmt/synopsis.py
k3fmt-0.1.4.dist-info/licenses/LICENSE
k3fmt-0.1.4.dist-info/METADATA
k3fmt-0.1.4.dist-info/WHEEL
k3fmt-0.1.4.dist-info/top_level.txt
k3fmt-0.1.4.dist-info/RECORD
